pergamon_server_extension/__init__.py
pergamon_server_extension/_version.py
pergamon_server_extension/completer.py
pergamon_server_extension/error_hook.py
pergamon_server_extension/handlers.py
pergamon_server_extension/help_handler.py
pergamon_server_extension/magic.py
pergamon_server_extension/chat_handlers/__init__.py
pergamon_server_extension/chat_handlers/train_sql.py
pergamon_server_extension/labextension/package.json
pergamon_server_extension/labextension/static/509.15c23cd5f645297b786d.js
pergamon_server_extension/labextension/static/728.cb881fc5659782c96787.js
pergamon_server_extension/labextension/static/remoteEntry.0c0276925d239e94bc63.js
pergamon_server_extension/labextension/static/style.js
pergamon_server_extension/labextension/static/third-party-licenses.json
pergamon_server_extension-0.1.13.data/data/etc/jupyter/jupyter_server_config.d/pergamon_server_extension.json
pergamon_server_extension-0.1.13.data/data/share/jupyter/labextensions/pergamon_server_extension/package.json
pergamon_server_extension-0.1.13.data/data/share/jupyter/labextensions/pergamon_server_extension/static/509.15c23cd5f645297b786d.js
pergamon_server_extension-0.1.13.data/data/share/jupyter/labextensions/pergamon_server_extension/static/728.cb881fc5659782c96787.js
pergamon_server_extension-0.1.13.data/data/share/jupyter/labextensions/pergamon_server_extension/static/remoteEntry.0c0276925d239e94bc63.js
pergamon_server_extension-0.1.13.data/data/share/jupyter/labextensions/pergamon_server_extension/static/style.js
pergamon_server_extension-0.1.13.data/data/share/jupyter/labextensions/pergamon_server_extension/static/third-party-licenses.json
pergamon_server_extension-0.1.13.data/data/share/jupyter/labextensions/pergamon_server_extension/install.json
pergamon_server_extension-0.1.13.dist-info/METADATA
pergamon_server_extension-0.1.13.dist-info/WHEEL
pergamon_server_extension-0.1.13.dist-info/licenses/LICENSE
pergamon_server_extension-0.1.13.dist-info/RECORD
