Metadata-Version: 2.4
Name: pergamon_server_extension
Version: 0.1.13
Summary: Calliope server extension
Project-URL: Homepage, https://github.com/calliopeai/junohub
Project-URL: Bug Tracker, https://github.com/calliopeai/junohub/issues
Project-URL: Repository, https://github.com/calliopeai/junohub.git
Author: pergamon_server_extension
License: BSD 3-Clause License
License-File: LICENSE
Keywords: jupyter,jupyterlab,jupyterlab-extension
Classifier: Framework :: Jupyter
Classifier: Framework :: Jupyter :: JupyterLab
Classifier: Framework :: Jupyter :: JupyterLab :: 4
Classifier: Framework :: Jupyter :: JupyterLab :: Extensions
Classifier: Framework :: Jupyter :: JupyterLab :: Extensions :: Prebuilt
Classifier: License :: OSI Approved :: BSD License
Classifier: Programming Language :: Python
Classifier: Programming Language :: Python :: 3
Classifier: Programming Language :: Python :: 3.8
Classifier: Programming Language :: Python :: 3.9
Classifier: Programming Language :: Python :: 3.10
Classifier: Programming Language :: Python :: 3.11
Classifier: Programming Language :: Python :: 3.12
Requires-Python: >=3.8
Requires-Dist: ipython
Requires-Dist: jupyter-server<3,>=2.0.1
Requires-Dist: requests>=2.25.0
